Ftntconfig/Ftnt_ssh.py
Ftntconfig/Ftntconfig.py
Ftntconfig/Ftntconfig_firewall.py
Ftntconfig/__init__.py
ftntconfig-1.3.dist-info/LICENSE
ftntconfig-1.3.dist-info/METADATA
ftntconfig-1.3.dist-info/WHEEL
ftntconfig-1.3.dist-info/top_level.txt
ftntconfig-1.3.dist-info/RECORD
