Metadata-Version: 2.1
Name: ftntconfig
Version: 1.3
Summary: Package ftntconfig
Home-page: https://github.com/cgustave/ftntconfig
Author: Cedric GUSTAVE
Author-email: cgustave@free.fr
Classifier: Development Status :: 4 - Beta
Classifier: Programming Language :: Python :: 3
Classifier: License :: OSI Approved :: MIT License
Classifier: Operating System :: POSIX :: Linux
Classifier: Natural Language :: English
Classifier: Topic :: System :: Networking
Requires-Python: >=3.5
License-File: LICENSE
